tl_exp/__init__.py
tl_exp/experiments.py
tl_exp/main.py
tl_exp-5.dist-info/METADATA
tl_exp-5.dist-info/WHEEL
tl_exp-5.dist-info/top_level.txt
tl_exp-5.dist-info/RECORD
